dominiquebuob/README.py
dominiquebuob/__init__.py
dominiquebuob/main.py
dominiquebuob-0.0.1.dist-info/License.txt
dominiquebuob-0.0.1.dist-info/METADATA
dominiquebuob-0.0.1.dist-info/WHEEL
dominiquebuob-0.0.1.dist-info/top_level.txt
dominiquebuob-0.0.1.dist-info/RECORD
