Metadata-Version: 2.2
Name: dominiquebuob
Version: 0.0.1
Summary: Dominique Buob, Computer Scientist with a edge for incentive structures
Author: Dominique Buob
Author-email: dominique.buob@gmail.com
Keywords: python,cv,computer-science
Classifier: Development Status :: 1 - Planning
License-File: License.txt
Dynamic: author
Dynamic: author-email
Dynamic: classifier
Dynamic: description
Dynamic: keywords
Dynamic: summary
